sum_dirac_dfcoef/__about__.py
sum_dirac_dfcoef/__init__.py
sum_dirac_dfcoef/__main__.py
sum_dirac_dfcoef/args.py
sum_dirac_dfcoef/atoms.py
sum_dirac_dfcoef/coefficient.py
sum_dirac_dfcoef/data.py
sum_dirac_dfcoef/eigenvalues.py
sum_dirac_dfcoef/electron_num.py
sum_dirac_dfcoef/file_writer.py
sum_dirac_dfcoef/functions_info.py
sum_dirac_dfcoef/header_info.py
sum_dirac_dfcoef/moltra.py
sum_dirac_dfcoef/privec_reader.py
sum_dirac_dfcoef/scheme.py
sum_dirac_dfcoef/subshell.py
sum_dirac_dfcoef/sum_dirac_dfcoef.py
sum_dirac_dfcoef/utils.py
sum_dirac_dfcoef-5.2.1.dist-info/METADATA
sum_dirac_dfcoef-5.2.1.dist-info/WHEEL
sum_dirac_dfcoef-5.2.1.dist-info/entry_points.txt
sum_dirac_dfcoef-5.2.1.dist-info/licenses/LICENSE
sum_dirac_dfcoef-5.2.1.dist-info/RECORD
