Metadata-Version: 2.3
Name: sum_dirac_dfcoef
Version: 5.2.1
Summary: This is a utility to summarize the contribution of each atomic orbital per molecular orbital from the DIRAC output file that the .ANALYZE option and *PRIVEC and .VECPRI options are used.
Project-URL: Documentation, https://github.com/RQC-HU/sum_dirac_dfcoef#readme
Project-URL: Issues, https://github.com/RQC-HU/sum_dirac_dfcoef/issues
Project-URL: Source, https://github.com/RQC-HU/sum_dirac_dfcoef
Author-email: Kohei Noda <kohei-noda@hiroshima-u.ac.jp>
License: LGPL-2.1-or-later
Classifier: Development Status :: 4 - Beta
Classifier: Programming Language :: Python
Classifier: Programming Language :: Python :: 3.7
Classifier: Programming Language :: Python :: 3.8
Classifier: Programming Language :: Python :: 3.9
Classifier: Programming Language :: Python :: 3.10
Classifier: Programming Language :: Python :: 3.11
Classifier: Programming Language :: Python :: 3.12
Classifier: Programming Language :: Python :: 3.13
Classifier: Programming Language :: Python :: Implementation :: CPython
Classifier: Programming Language :: Python :: Implementation :: PyPy
Requires-Python: >=3.7
Requires-Dist: pydantic
Provides-Extra: dev
Requires-Dist: black>=23.1.0; extra == 'dev'
Requires-Dist: coverage[toml]>=6.5; extra == 'dev'
Requires-Dist: mypy>=1.0.0; extra == 'dev'
Requires-Dist: pytest; extra == 'dev'
Requires-Dist: ruff>=0.0.243; extra == 'dev'
Provides-Extra: test
Requires-Dist: coverage[toml]>=6.5; extra == 'test'
Requires-Dist: pytest; extra == 'test'
